gymagent/__init__.py
gymagent/acrobot.py
gymagent/bipedal_walker.py
gymagent/cartpole.py
gymagent/lunarlander.py
gymagent/mountaincar.py
gymagent/pendulum.py
gymagent/pong.py
gymagent/version.py
gymagent-1.0.0.dist-info/METADATA
gymagent-1.0.0.dist-info/WHEEL
gymagent-1.0.0.dist-info/top_level.txt
gymagent-1.0.0.dist-info/RECORD
