Metadata-Version: 2.1
Name: gymagent
Version: 1.0.0
Summary: gymagent
Home-page: https://github.com/ZhiqingXiao/OpenAIGymSolution
Author: Zhiqing Xiao
Author-email: xzq.xiaozhiqing@gmail.com
Classifier: Programming Language :: Python
Classifier: Intended Audience :: Science/Research
